pixela/__init__.py
pixela/client.py
pixela-1.2.0.dist-info/LICENSE
pixela-1.2.0.dist-info/METADATA
pixela-1.2.0.dist-info/WHEEL
pixela-1.2.0.dist-info/top_level.txt
pixela-1.2.0.dist-info/RECORD
