Metadata-Version: 2.1
Name: pixela
Version: 1.2.0
Summary: Pixela API client for Python.
Home-page: http://github.com/heavenshell/py-pixela
Author: Shinya Ohyanagi
Author-email: sohyanagi@gmail.com
License: BSD
Platform: any
Classifier: Development Status :: 4 - Beta
Classifier: Environment :: Web Environment
Classifier: Intended Audience :: Developers
Classifier: License :: OSI Approved :: BSD License
Classifier: Operating System :: OS Independent
Classifier: Programming Language :: Python
Classifier: Topic :: Internet :: WWW/HTTP
Requires-Dist: mock
Requires-Dist: requests
Requires-Dist: pytz
